imvis/__init__.py
imvis/dicomdir_split.py
imvis/imagesc3s.py
imvis/mipz.py
imvis/nifti_convert.py
imvis/util.py
imvis-0.0.9.3.dist-info/METADATA
imvis-0.0.9.3.dist-info/WHEEL
imvis-0.0.9.3.dist-info/entry_points.txt
imvis-0.0.9.3.dist-info/licenses/LICENSE
imvis-0.0.9.3.dist-info/RECORD
