Metadata-Version: 2.4
Name: imvis
Version: 0.0.9.3
Summary: Interactive visualization and processing of 3D medical images in python
Author-email: Xiangxi Meng <mengxiangxi@pku.edu.cn>
License-File: LICENSE
Requires-Python: >=3.8
Requires-Dist: dicom2nifti>=2.4.10
Requires-Dist: matplotlib>=3.7.5
Requires-Dist: numpy>=1.24.4
Requires-Dist: pydicom>=2.4.4
Requires-Dist: scipy>=1.10.1
Requires-Dist: simpleitk>=2.0.2
